Workbook

Sheet Assumptions
A1: Assumptions
A2: Brighter Nights Lighting Technologies · Lighting Partner Program · rebuilt 2026-09-26 (100% fee credit, Site Value Evaluator ledger)
A4: Fee tiers (marginal, like tax brackets) | B4: Band width | C4: Rate | D4: Notes
A5: First $250,000 | B5: 250000 | C5: 0.07 | D5: Rates are inputs. Change C5:C9 and every tab recalculates.
A6: $250,000 to $500,000 | B6: 250000 | C6: 0.06
A7: $500,000 to $750,000 | B7: 250000 | C7: 0.05
A8: $750,000 to $1,000,000 | B8: 250000 | C8: 0.04
A9: Above $1,000,000 | B9: 1000000000 | C9: 0.03
A11: Program inputs | B11: Value | D11: Notes
A12: Reinvestment share of fee into partner ads | B12: 0.3 | D12: Partner matches this amount
A13: Fee credit rate toward ledger | B13: 1 | D13: RULED 2026-09-26: 100% of every fee dollar
A14: Trailing months of fee added at buyout | B14: 3
A15: Soft cap, flag add ons projecting buyout past year | B15: 7
A16: Add ons per year (light) | B16: 5000 | D16: Routine maintenance never counts
A17: Add ons per year (CRM level) | B17: 20000
A19: Ledger (Site Value Evaluator) | B19: Value | D19: Notes
A20: Part 1 Market replacement cost of what was built | B20: 102650 | D20: Base package, 13 items, midpoint of 2026 agency and freelance rates
A21: Part 2 Contractor hours not spent teaching an agency | B21: 180 | D21: hours
A22: Contractor hourly value | B22: 150 | D22: per hour
A23: Part 3 Months of agency delay avoided | B23: 5 | D23: months
A24: Monthly gross used to price delay | B24: 41000 | D24: about $492K a year
A25: Share of gross driven by the site | B25: 0.35
A27: Contractor time value | B27: =B21*B22 -> 27000
A28: Revenue not lost to delay | B28: =B23*B24*B25 -> 71750
A29: LEDGER OPENING VALUE | B29: =B20+B27+B28 -> 201400

Sheet Projection
A1: Five year projection and earn out
A2: Brighter Nights Lighting Technologies · Lighting Partner Program · rebuilt 2026-09-26 (100% fee credit, Site Value Evaluator ledger)
B4: Year 1 | C4: Year 2 | D4: Year 3 | E4: Year 4 | F4: Year 5 | G4: Total
A5: Partner gross lighting revenue | B5: 500000 | C5: 750000 | D5: 1000000 | E5: 1300000 | F5: 1600000 | G5: =SUM(B5:F5) -> 5150000
A6: Program fee (marginal tiers) | B6: =MIN(B5,Assumptions!$B$5)*Assumptions!$C$5+MIN(MAX(B5-Assumptions!$B$5,0),Assumptions!$B$6)*Assumptions!$C$6+MIN(MAX(B5-Assumptions!$B$5-Assumptions!$B$6,0),Assumptions!$B$7)*Assumptions!$C$7+MIN(MAX(B5-Assumptions!$B$5-Assumptions!$B$6-Assumptions!$B$7,0),Assumptions!$B$8)*Assumptions!$C$8+MAX(B5-Assumptions!$B$5-Assumptions!$B$6-Assumptions!$B$7-Assumptions!$B$8,0)*Assumptions!$C$9 -> 32500 | C6: =MIN(C5,Assumptions!$B$5)*Assumptions!$C$5+MIN(MAX(C5-Assumptions!$B$5,0),Assumptions!$B$6)*Assumptions!$C$6+MIN(MAX(C5-Assumptions!$B$5-Assumptions!$B$6,0),Assumptions!$B$7)*Assumptions!$C$7+MIN(MAX(C5-Assumptions!$B$5-Assumptions!$B$6-Assumptions!$B$7,0),Assumptions!$B$8)*Assumptions!$C$8+MAX(C5-Assumptions!$B$5-Assumptions!$B$6-Assumptions!$B$7-Assumptions!$B$8,0)*Assumptions!$C$9 -> 45000 | D6: =MIN(D5,Assumptions!$B$5)*Assumptions!$C$5+MIN(MAX(D5-Assumptions!$B$5,0),Assumptions!$B$6)*Assumptions!$C$6+MIN(MAX(D5-Assumptions!$B$5-Assumptions!$B$6,0),Assumptions!$B$7)*Assumptions!$C$7+MIN(MAX(D5-Assumptions!$B$5-Assumptions!$B$6-Assumptions!$B$7,0),Assumptions!$B$8)*Assumptions!$C$8+MAX(D5-Assumptions!$B$5-Assumptions!$B$6-Assumptions!$B$7-Assumptions!$B$8,0)*Assumptions!$C$9 -> 55000 | E6: =MIN(E5,Assumptions!$B$5)*Assumptions!$C$5+MIN(MAX(E5-Assumptions!$B$5,0),Assumptions!$B$6)*Assumptions!$C$6+MIN(MAX(E5-Assumptions!$B$5-Assumptions!$B$6,0),Assumptions!$B$7)*Assumptions!$C$7+MIN(MAX(E5-Assumptions!$B$5-Assumptions!$B$6-Assumptions!$B$7,0),Assumptions!$B$8)*Assumptions!$C$8+MAX(E5-Assumptions!$B$5-Assumptions!$B$6-Assumptions!$B$7-Assumptions!$B$8,0)*Assumptions!$C$9 -> 64000 | F6: =MIN(F5,Assumptions!$B$5)*Assumptions!$C$5+MIN(MAX(F5-Assumptions!$B$5,0),Assumptions!$B$6)*Assumptions!$C$6+MIN(MAX(F5-Assumptions!$B$5-Assumptions!$B$6,0),Assumptions!$B$7)*Assumptions!$C$7+MIN(MAX(F5-Assumptions!$B$5-Assumptions!$B$6-Assumptions!$B$7,0),Assumptions!$B$8)*Assumptions!$C$8+MAX(F5-Assumptions!$B$5-Assumptions!$B$6-Assumptions!$B$7-Assumptions!$B$8,0)*Assumptions!$C$9 -> 73000 | G6: =SUM(B6:F6) -> 269500
A7: Blended fee rate | B7: =B6/B5 -> 0.065 | C7: =C6/C5 -> 0.06 | D7: =D6/D5 -> 0.055 | E7: =E6/E5 -> 0.049230769 | F7: =F6/F5 -> 0.045625
A8: Partner profit after fee | B8: =B5-B6 -> 467500 | C8: =C5-C6 -> 705000 | D8: =D5-D6 -> 945000 | E8: =E5-E6 -> 1236000 | F8: =F5-F6 -> 1527000 | G8: =SUM(B8:F8) -> 4880500
A9: Our reinvestment into partner ads | B9: =B6*Assumptions!$B$12 -> 9750 | C9: =C6*Assumptions!$B$12 -> 13500 | D9: =D6*Assumptions!$B$12 -> 16500 | E9: =E6*Assumptions!$B$12 -> 19200 | F9: =F6*Assumptions!$B$12 -> 21900 | G9: =SUM(B9:F9) -> 80850
A10: Partner marketing match | B10: =B6*Assumptions!$B$12 -> 9750 | C10: =C6*Assumptions!$B$12 -> 13500 | D10: =D6*Assumptions!$B$12 -> 16500 | E10: =E6*Assumptions!$B$12 -> 19200 | F10: =F6*Assumptions!$B$12 -> 21900 | G10: =SUM(B10:F10) -> 80850
A11: Fee credit to ledger | B11: =B6*Assumptions!$B$13 -> 32500 | C11: =C6*Assumptions!$B$13 -> 45000 | D11: =D6*Assumptions!$B$13 -> 55000 | E11: =E6*Assumptions!$B$13 -> 64000 | F11: =F6*Assumptions!$B$13 -> 73000 | G11: =SUM(B11:F11) -> 269500
A12: Cumulative credit | B12: =SUM($B$11:B11) -> 32500 | C12: =SUM($B$11:C11) -> 77500 | D12: =SUM($B$11:D11) -> 132500 | E12: =SUM($B$11:E11) -> 196500 | F12: =SUM($B$11:F11) -> 269500
A13: Ledger balance (no add ons) | B13: =Assumptions!$B$29 -> 201400 | C13: =Assumptions!$B$29 -> 201400 | D13: =Assumptions!$B$29 -> 201400 | E13: =Assumptions!$B$29 -> 201400 | F13: =Assumptions!$B$29 -> 201400
A14: Remaining to buy out | B14: =MAX(B13-B12,0) -> 168900 | C14: =MAX(C13-C12,0) -> 123900 | D14: =MAX(D13-D12,0) -> 68900 | E14: =MAX(E13-E12,0) -> 4900 | F14: =MAX(F13-F12,0) -> 0
A15: Buyout price today (remaining + trailing fee) | B15: =B14+B6*Assumptions!$B$14/12 -> 177025 | C15: =C14+C6*Assumptions!$B$14/12 -> 135150 | D15: =D14+D6*Assumptions!$B$14/12 -> 82650 | E15: =E14+E6*Assumptions!$B$14/12 -> 20900 | F15: =F14+F6*Assumptions!$B$14/12 -> 18250
A16: Owned outright? | B16: =IF(B12>=B13,"YES","not yet") -> not yet | C16: =IF(C12>=C13,"YES","not yet") -> not yet | D16: =IF(D12>=D13,"YES","not yet") -> not yet | E16: =IF(E12>=E13,"YES","not yet") -> not yet | F16: =IF(F12>=F13,"YES","not yet") -> YES
A18: Earn out year (interpolated, no add ons) | B18: =IF(F12<Assumptions!B29,"past year 5",IF(B12>=Assumptions!B29,B12/B11,IF(C12>=Assumptions!B29,1+(Assumptions!B29-B12)/C11,IF(D12>=Assumptions!B29,2+(Assumptions!B29-C12)/D11,IF(E12>=Assumptions!B29,3+(Assumptions!B29-D12)/E11,4+(Assumptions!B29-E12)/F11))))) -> 4.0671233
A19: Flat $492K gross, years to earn out | B19: =Assumptions!B29/(MIN(492000,Assumptions!B5)*Assumptions!C5+MIN(MAX(492000-Assumptions!B5,0),Assumptions!B6)*Assumptions!C6)/Assumptions!B13 -> 6.2898189
A21: With add ons (light pace)
A22: Ledger by year end | B22: =Assumptions!$B$29+Assumptions!$B$16*1 -> 206400 | C22: =Assumptions!$B$29+Assumptions!$B$16*2 -> 211400 | D22: =Assumptions!$B$29+Assumptions!$B$16*3 -> 216400 | E22: =Assumptions!$B$29+Assumptions!$B$16*4 -> 221400 | F22: =Assumptions!$B$29+Assumptions!$B$16*5 -> 226400
A23: Owned outright? | B23: =IF(B12>=B22,"YES","not yet") -> not yet | C23: =IF(C12>=C22,"YES","not yet") -> not yet | D23: =IF(D12>=D22,"YES","not yet") -> not yet | E23: =IF(E12>=E22,"YES","not yet") -> not yet | F23: =IF(F12>=F22,"YES","not yet") -> YES
A25: With add ons (CRM level pace)
A26: Ledger by year end | B26: =Assumptions!$B$29+Assumptions!$B$17*1 -> 221400 | C26: =Assumptions!$B$29+Assumptions!$B$17*2 -> 241400 | D26: =Assumptions!$B$29+Assumptions!$B$17*3 -> 261400 | E26: =Assumptions!$B$29+Assumptions!$B$17*4 -> 281400 | F26: =Assumptions!$B$29+Assumptions!$B$17*5 -> 301400
A27: Owned outright? | B27: =IF(B12>=B26,"YES","not yet") -> not yet | C27: =IF(C12>=C26,"YES","not yet") -> not yet | D27: =IF(D12>=D26,"YES","not yet") -> not yet | E27: =IF(E12>=E26,"YES","not yet") -> not yet | F27: =IF(F12>=F26,"YES","not yet") -> not yet

Sheet Fee by gross
A1: Fee at each gross level
A2: Brighter Nights Lighting Technologies · Lighting Partner Program · rebuilt 2026-09-26 (100% fee credit, Site Value Evaluator ledger)
A4: Annual gross | B4: Fee | C4: Blended rate | D4: Profit after fee
A5: 250000 | B5: =MIN(A5,Assumptions!$B$5)*Assumptions!$C$5+MIN(MAX(A5-Assumptions!$B$5,0),Assumptions!$B$6)*Assumptions!$C$6+MIN(MAX(A5-Assumptions!$B$5-Assumptions!$B$6,0),Assumptions!$B$7)*Assumptions!$C$7+MIN(MAX(A5-Assumptions!$B$5-Assumptions!$B$6-Assumptions!$B$7,0),Assumptions!$B$8)*Assumptions!$C$8+MAX(A5-Assumptions!$B$5-Assumptions!$B$6-Assumptions!$B$7-Assumptions!$B$8,0)*Assumptions!$C$9 -> 17500 | C5: =B5/A5 -> 0.07 | D5: =A5-B5 -> 232500
A6: 500000 | B6: =MIN(A6,Assumptions!$B$5)*Assumptions!$C$5+MIN(MAX(A6-Assumptions!$B$5,0),Assumptions!$B$6)*Assumptions!$C$6+MIN(MAX(A6-Assumptions!$B$5-Assumptions!$B$6,0),Assumptions!$B$7)*Assumptions!$C$7+MIN(MAX(A6-Assumptions!$B$5-Assumptions!$B$6-Assumptions!$B$7,0),Assumptions!$B$8)*Assumptions!$C$8+MAX(A6-Assumptions!$B$5-Assumptions!$B$6-Assumptions!$B$7-Assumptions!$B$8,0)*Assumptions!$C$9 -> 32500 | C6: =B6/A6 -> 0.065 | D6: =A6-B6 -> 467500
A7: 750000 | B7: =MIN(A7,Assumptions!$B$5)*Assumptions!$C$5+MIN(MAX(A7-Assumptions!$B$5,0),Assumptions!$B$6)*Assumptions!$C$6+MIN(MAX(A7-Assumptions!$B$5-Assumptions!$B$6,0),Assumptions!$B$7)*Assumptions!$C$7+MIN(MAX(A7-Assumptions!$B$5-Assumptions!$B$6-Assumptions!$B$7,0),Assumptions!$B$8)*Assumptions!$C$8+MAX(A7-Assumptions!$B$5-Assumptions!$B$6-Assumptions!$B$7-Assumptions!$B$8,0)*Assumptions!$C$9 -> 45000 | C7: =B7/A7 -> 0.06 | D7: =A7-B7 -> 705000
A8: 1000000 | B8: =MIN(A8,Assumptions!$B$5)*Assumptions!$C$5+MIN(MAX(A8-Assumptions!$B$5,0),Assumptions!$B$6)*Assumptions!$C$6+MIN(MAX(A8-Assumptions!$B$5-Assumptions!$B$6,0),Assumptions!$B$7)*Assumptions!$C$7+MIN(MAX(A8-Assumptions!$B$5-Assumptions!$B$6-Assumptions!$B$7,0),Assumptions!$B$8)*Assumptions!$C$8+MAX(A8-Assumptions!$B$5-Assumptions!$B$6-Assumptions!$B$7-Assumptions!$B$8,0)*Assumptions!$C$9 -> 55000 | C8: =B8/A8 -> 0.055 | D8: =A8-B8 -> 945000
A9: 1250000 | B9: =MIN(A9,Assumptions!$B$5)*Assumptions!$C$5+MIN(MAX(A9-Assumptions!$B$5,0),Assumptions!$B$6)*Assumptions!$C$6+MIN(MAX(A9-Assumptions!$B$5-Assumptions!$B$6,0),Assumptions!$B$7)*Assumptions!$C$7+MIN(MAX(A9-Assumptions!$B$5-Assumptions!$B$6-Assumptions!$B$7,0),Assumptions!$B$8)*Assumptions!$C$8+MAX(A9-Assumptions!$B$5-Assumptions!$B$6-Assumptions!$B$7-Assumptions!$B$8,0)*Assumptions!$C$9 -> 62500 | C9: =B9/A9 -> 0.05 | D9: =A9-B9 -> 1187500
A10: 1500000 | B10: =MIN(A10,Assumptions!$B$5)*Assumptions!$C$5+MIN(MAX(A10-Assumptions!$B$5,0),Assumptions!$B$6)*Assumptions!$C$6+MIN(MAX(A10-Assumptions!$B$5-Assumptions!$B$6,0),Assumptions!$B$7)*Assumptions!$C$7+MIN(MAX(A10-Assumptions!$B$5-Assumptions!$B$6-Assumptions!$B$7,0),Assumptions!$B$8)*Assumptions!$C$8+MAX(A10-Assumptions!$B$5-Assumptions!$B$6-Assumptions!$B$7-Assumptions!$B$8,0)*Assumptions!$C$9 -> 70000 | C10: =B10/A10 -> 0.046666667 | D10: =A10-B10 -> 1430000
A11: 2000000 | B11: =MIN(A11,Assumptions!$B$5)*Assumptions!$C$5+MIN(MAX(A11-Assumptions!$B$5,0),Assumptions!$B$6)*Assumptions!$C$6+MIN(MAX(A11-Assumptions!$B$5-Assumptions!$B$6,0),Assumptions!$B$7)*Assumptions!$C$7+MIN(MAX(A11-Assumptions!$B$5-Assumptions!$B$6-Assumptions!$B$7,0),Assumptions!$B$8)*Assumptions!$C$8+MAX(A11-Assumptions!$B$5-Assumptions!$B$6-Assumptions!$B$7-Assumptions!$B$8,0)*Assumptions!$C$9 -> 85000 | C11: =B11/A11 -> 0.0425 | D11: =A11-B11 -> 1915000

Sheet Agency comparison
A1: Three year cost, program vs agency vs DIY
A2: Brighter Nights Lighting Technologies · Lighting Partner Program · rebuilt 2026-09-26 (100% fee credit, Site Value Evaluator ledger)
B4: Lighting Partner Program | C4: Typical agency | D4: Do it yourself
A5: Agency monthly retainer | C5: 4000
A6: Agency setup and site build | C6: 12000
A7: DIY build cost (Part 1 replacement) | D7: =Assumptions!B20 -> 102650
A8: Owner time teaching or building (Part 2) | C8: =Assumptions!B27 -> 27000 | D8: =Assumptions!B27*2 -> 54000
A9: Revenue lost to delay (Part 3) | C9: =Assumptions!B28 -> 71750 | D9: =Assumptions!B28*1.5 -> 107625
A11: Three year fees paid | B11: =SUM(Projection!B6:D6) -> 132500 | C11: =C5*36+C6 -> 156000 | D11: 0
A12: Ads funded by provider over three years | B12: =SUM(Projection!B9:D9) -> 39750 | C12: 0 | D12: 0
A13: Hidden costs (time and delay) | B13: 0 | C13: =C8+C9 -> 98750 | D13: =D7+D8+D9 -> 264275
A14: Net three year cost | B14: =B11-B12+B13 -> 92750 | C14: =C11-C12+C13 -> 254750 | D14: =D11-D12+D13 -> 264275
A15: Credit toward owning the site | B15: =SUM(Projection!B11:D11) -> 132500 | C15: 0 | D15: 0
A16: Asset owned at end (ledger credited) | B16: =MIN(B15,Assumptions!B29) -> 132500 | C16: 0 | D16: =D7 -> 102650
A18: Program is cheaper than the agency by | B18: =C14-B14 -> 162000
